windsaloft/__init__.py
windsaloft/contour.py
windsaloft/jetstream.py
windsaloft/utils.py
windsaloft-0.0.2.dist-info/LICENSE
windsaloft-0.0.2.dist-info/METADATA
windsaloft-0.0.2.dist-info/WHEEL
windsaloft-0.0.2.dist-info/top_level.txt
windsaloft-0.0.2.dist-info/RECORD
