Metadata-Version: 2.1
Name: windsaloft
Version: 0.0.2
Summary: Convert U/V raster to streamlines (geojson)
Home-page: https://github.com/olehz/windsaloft
Author: Oleh Zamkovyi
Author-email: oleh.zam@gmail.com
License: MIT
Keywords: map weather geojson gis gfs streamline
Platform: UNKNOWN
Classifier: License :: OSI Approved :: MIT License
Classifier: Programming Language :: Python :: 3
Requires-Dist: geojson
Provides-Extra: test
Requires-Dist: numpy ; extra == 'test'
Requires-Dist: pytest ; extra == 'test'
